arnhem/__init__.py
arnhem/arnhem.py
arnhem/exceptions.py
arnhem/models.py
arnhem/py.typed
arnhem-1.0.0.dist-info/METADATA
arnhem-1.0.0.dist-info/WHEEL
arnhem-1.0.0.dist-info/licenses/LICENSE
arnhem-1.0.0.dist-info/RECORD
